odoo/addons/account_financial_report/README.rst
odoo/addons/account_financial_report/__init__.py
odoo/addons/account_financial_report/__manifest__.py
odoo/addons/account_financial_report/menuitems.xml
odoo/addons/account_financial_report/reports.xml
odoo/addons/account_financial_report/i18n/account_financial_report.pot
odoo/addons/account_financial_report/i18n/ar.po
odoo/addons/account_financial_report/i18n/ca.po
odoo/addons/account_financial_report/i18n/ca_AD.po
odoo/addons/account_financial_report/i18n/ca_ES.po
odoo/addons/account_financial_report/i18n/de.po
odoo/addons/account_financial_report/i18n/es.po
odoo/addons/account_financial_report/i18n/es_AR.po
odoo/addons/account_financial_report/i18n/es_MX.po
odoo/addons/account_financial_report/i18n/fr.po
odoo/addons/account_financial_report/i18n/fr_CH.po
odoo/addons/account_financial_report/i18n/hr.po
odoo/addons/account_financial_report/i18n/hr_HR.po
odoo/addons/account_financial_report/i18n/it.po
odoo/addons/account_financial_report/i18n/ja.po
odoo/addons/account_financial_report/i18n/nl.po
odoo/addons/account_financial_report/i18n/nl_NL.po
odoo/addons/account_financial_report/i18n/pt.po
odoo/addons/account_financial_report/i18n/pt_BR.po
odoo/addons/account_financial_report/i18n/ro.po
odoo/addons/account_financial_report/i18n/sl.po
odoo/addons/account_financial_report/i18n/sv.po
odoo/addons/account_financial_report/i18n/tr.po
odoo/addons/account_financial_report/models/__init__.py
odoo/addons/account_financial_report/models/account.py
odoo/addons/account_financial_report/models/account_age_report_configuration.py
odoo/addons/account_financial_report/models/account_group.py
odoo/addons/account_financial_report/models/account_move_line.py
odoo/addons/account_financial_report/models/ir_actions_report.py
odoo/addons/account_financial_report/models/res_config_settings.py
odoo/addons/account_financial_report/readme/CONFIGURE.md
odoo/addons/account_financial_report/readme/CONTRIBUTORS.md
odoo_addon_account_financial_report-18.0.1.4.7.dist-info/METADATA
odoo_addon_account_financial_report-18.0.1.4.7.dist-info/WHEEL
odoo_addon_account_financial_report-18.0.1.4.7.dist-info/top_level.txt
odoo_addon_account_financial_report-18.0.1.4.7.dist-info/RECORD
