Metadata-Version: 2.1
Name: odoo-addon-account_financial_report
Version: 18.0.1.4.7
Requires-Python: >=3.10
Requires-Dist: odoo-addon-date_range==18.0.*
Requires-Dist: odoo-addon-report_xlsx==18.0.*
Requires-Dist: odoo==18.0.*
Summary: OCA Financial Reports
Home-page: https://github.com/OCA/account-financial-reporting
License: AGPL-3
Author: Camptocamp,initOS GmbH,redCOR AG,ForgeFlow,Odoo Community Association (OCA)
Author-email: support@odoo-community.org
Classifier: Programming Language :: Python
Classifier: Framework :: Odoo
Classifier: Framework :: Odoo :: 18.0
Classifier: License :: OSI Approved :: GNU Affero General Public License v3
